dis3.py
dis3-0.1.2.dist-info/DESCRIPTION.rst
dis3-0.1.2.dist-info/METADATA
dis3-0.1.2.dist-info/RECORD
dis3-0.1.2.dist-info/WHEEL
dis3-0.1.2.dist-info/metadata.json
dis3-0.1.2.dist-info/top_level.txt
