Metadata-Version: 1.1
Name: dis3
Version: 0.1.2
Summary: Python 2.7 backport of the "dis" module from Python 3.5+
Home-page: https://github.com/tomxtobin/dis3
Author: Tom X. Tobin
Author-email: tomxtobin@tomxtobin.com
License: MIT
Platform: UNKNOWN
Classifier: Development Status :: 4 - Beta
Classifier: Intended Audience :: Developers
Classifier: License :: OSI Approved :: MIT License
Classifier: License :: OSI Approved :: Python Software Foundation License
Classifier: Programming Language :: Python :: 2
Classifier: Programming Language :: Python :: 2.7
Classifier: Programming Language :: Python :: 2 :: Only
Classifier: Topic :: Software Development :: Disassemblers
Classifier: Topic :: Software Development :: Libraries :: Python Modules
